<?xml version="1.0" encoding="UTF-8"?>
<task type="london">
<stage type="early-analysis">
</stage>
<stage type="scf">
<quantity label="electronic-energy" unit="Hartree">
-9.1966446738592680e+01</quantity>
<quantity label="kinetic-energy" unit="Hartree">
8.0371047081117496e+01</quantity>
<quantity label="scalar-potential-energy" unit="Hartree">
-2.1524590546747308e+02</quantity>
<quantity label="spin-zeeman-energy" unit="Hartree">
8.8817841970012525e-18</quantity>
<quantity label="coulomb-self-repulsion-energy" unit="Hartree">
5.2606327549718245e+01</quantity>
<quantity label="homo-lumo-gap-down" unit="Hartree">
6.1119444909807230e-01</quantity>
<quantity label="homo-lumo-gap-up" unit="Hartree">
6.1119444909788911e-01</quantity>
<properties>
<quantity label="spin projection on field" unit="dimensionless">
-8.8817841970012523e-16</quantity>
<quantity label="spin projection squared" unit="dimensionless">
-1.8651746813702630e-14</quantity>
<quantity label="total spin" unit="dimensionless">
-3.4638958368304884e-14</quantity>
<property type="angular momentum" unit="au">
<matrix type="complex" rows="3" columns="1" packing="column">
-1.4941659327358277e-15
-5.6703183843334384e-14
8.9348865832553678e-02
</matrix>
</property>
<property type="coordinate derivative contribution to angular momentum" unit="au">
<matrix type="complex" rows="3" columns="1" packing="column">
-2.7419944726465587e-16
-3.5414567217828473e-14
-4.3916143513823376e-03
</matrix>
</property>
<property type="electronic dipole moment" unit="au">
<matrix type="complex" rows="3" columns="1" packing="column">
9.6165457679295130e-14
2.6771967209277965e-14
6.4064700501900329e-01
</matrix>
</property>
<property type="nuclear dipole moment" unit="au">
<matrix type="complex" rows="3" columns="1" packing="column">
0.0000000000000000e+00
0.0000000000000000e+00
0.0000000000000000e+00
</matrix>
</property>
</properties>
</stage>
</task>
